hawc2models/__init__.py
hawc2models/utils.py
hawc2models/version.py
hawc2models/reference_models/__init__.py
hawc2models/reference_models/_reference_model.py
hawc2models/reference_models/dtu10mw.py
hawc2models/reference_models/iea22mw.py
hawc2models-0.0.4.dist-info/licenses/LICENSE
hawc2models-0.0.4.dist-info/METADATA
hawc2models-0.0.4.dist-info/WHEEL
hawc2models-0.0.4.dist-info/top_level.txt
hawc2models-0.0.4.dist-info/RECORD
